src/mem.v
`timescale 1ns / 1ps

module mem(
  input clk, 
  input rstb,
  input wen, 
  input ren,
  input [31:0] addr,
  input [31:0] wdata,
  output reg [31:0] rdata
);

  localparam MEMWORDS     = 16384;
  reg [31:0] mem [0:MEMWORDS-1];

  initial begin 
    $readmemh("rom/program.hex", mem);
  end

  always @(posedge clk or negedge rstb) begin
    if (!rstb) begin
      rdata <= 32'h0;
    end

    else begin
      if (addr[31:16] <= 14'h00003FFF) begin // Valid r/w RAM address
        case ({wen, ren})
          2'b00: rdata <= 32'h0;
          2'b01: rdata <= mem[addr[31:2]];
          2'b10: mem[addr[31:2]] <= wdata;
          2'b11: begin
            mem[addr[31:2]] <= wdata;
            rdata <= mem[addr[31:2]];
          end
        endcase
      end else begin
        $display("Unmapped region access at 0x%08hx", addr);
        case ({wen, ren})
          2'b00: rdata <= 32'hDEADBEEF;
          2'b01: rdata <= 32'hDEADBEEF;
          2'b10: rdata <= 32'hDEADBEEF;
          2'b11: rdata <= 32'hDEADBEEF;
        endcase
      end
    end
  end

endmodule

tb/mem_tb.v
`timescale 1ns / 1ps

module mem_tb ();
  reg         clk;
  reg         rstb;
  reg         we;
  reg         re;
  reg  [31:0] addr;
  reg  [31:0] wdata;
  wire [31:0] rdata;

  mem MEM (
      .clk(clk),
      .rstb(rstb),
      .wen(we),
      .ren(re),
      .addr(addr),
      .wdata(wdata),
      .rdata(rdata)
  );

  always #5 clk = ~clk;

  task write_word;
    input [31:0] address;
    input [31:0] data;
    begin
      @(negedge clk);
      addr  = address;
      wdata = data;
      we    = 1;
      re    = 0;
      @(posedge clk);
      #1;
      we = 0;
    end
  endtask

  task read_word;
    input [31:0] address;
    begin
      @(negedge clk);
      addr  = address;
      wdata = 32'h0;
      we    = 0;
      re    = 1;
      @(posedge clk);
      #1;
      re = 0;
    end
  endtask

  task check;
    input [31:0] expected;
    input [63:0] test_name;
    begin
      if (rdata == expected) $display("PASS [%s]: got 0x%08X", test_name, rdata);
      else $display("FAIL [%s]: expected 0x%08X got 0x%08X", test_name, expected, rdata);
    end
  endtask

  initial begin
    $dumpfile("build/mem_tb.vcd");
    $dumpvars(0, mem_tb);

    clk   = 0;
    rstb  = 0;
    we    = 0;
    re    = 0;
    addr  = 0;
    wdata = 0;

    // hold reset
    repeat (2) @(posedge clk);
    rstb = 1;
    repeat (2) @(posedge clk);

    // test 1: readmemh load — word 0
    read_word(32'h00000000);
    check(32'hAABBCCDD, "readmemh[0]");

    // test 2: readmemh load — word 1
    read_word(32'h00000004);
    check(32'h11223344, "readmemh[1]");

    // test 3: readmemh load — word 2
    read_word(32'h00000008);
    check(32'hDEADBEEF, "readmemh[2]");

    // test 4: write then read back
    write_word(32'h00000010, 32'h12345678);
    read_word(32'h00000010);
    check(32'h12345678, "write/read ");

    // test 5: overwrite and read back
    write_word(32'h00000010, 32'hCAFEBABE);
    read_word(32'h00000010);
    check(32'hCAFEBABE, "overwrite  ");

    // test 6: simultaneous we+re — should return old data
    write_word(32'h00000020, 32'hAAAAAAAA);
    @(negedge clk);
    addr  = 32'h00000020;
    wdata = 32'hBBBBBBBB;
    we    = 1;
    re    = 1;
    @(posedge clk);
    #1;
    we = 0;
    re = 0;
    check(32'hAAAAAAAA, "old data   ");

    // test 7: unmapped access — should warn and return 0xDEADBEEF
    read_word(32'hDEAD0000);
    check(32'hDEADBEEF, "unmapped   ");

    repeat (2) @(posedge clk);
    $finish;
  end

endmodule

build/mem_tb.vcd
$date
	Thu Apr 30 19:02:28 2026
$end
$version
	Icarus Verilog
$end
$timescale
	1ps
$end
$scope module mem_tb $end
$var wire 32 ! rdata [31:0] $end
$var reg 32 " addr [31:0] $end
$var reg 1 # clk $end
$var reg 1 $ re $end
$var reg 1 % rstb $end
$var reg 32 & wdata [31:0] $end
$var reg 1 ' we $end
$scope module MEM $end
$var wire 32 ( addr [31:0] $end
$var wire 1 # clk $end
$var wire 1 $ ren $end
$var wire 1 % rstb $end
$var wire 32 ) wdata [31:0] $end
$var wire 1 ' wen $end
$var parameter 32 * MEMWORDS $end
$var reg 32 + rdata [31:0] $end
$upscope $end
$scope task check $end
$var reg 32 , expected [31:0] $end
$var reg 64 - test_name [63:0] $end
$upscope $end
$scope task read_word $end
$var reg 32 . address [31:0] $end
$upscope $end
$scope task write_word $end
$var reg 32 / address [31:0] $end
$var reg 32 0 data [31:0] $end
$upscope $end
$upscope $end
$enddefinitions $end
$comment Show the parameter values. $end
$dumpall
b100000000000000 *
$end
#0
$dumpvars
bx 0
bx /
bx .
bx -
bx ,
b0 +
b0 )
b0 (
0'
b0 &
0%
0$
0#
b0 "
b0 !
$end
#5000
1#
#10000
0#
#15000
1%
1#
#20000
0#
#25000
1#
#30000
0#
#35000
b0 .
1#
#40000
1$
0#
#45000
b10101010101110111100110011011101 !
b10101010101110111100110011011101 +
1#
#46000
b100 .
b110010001101101011001010110110101101000010110110011000001011101 -
b10101010101110111100110011011101 ,
0$
#50000
1$
b100 "
b100 (
0#
#55000
b10001001000100011001101000100 !
b10001001000100011001101000100 +
1#
#56000
b1000 .
b110010001101101011001010110110101101000010110110011000101011101 -
b10001001000100011001101000100 ,
0$
#60000
1$
b1000 "
b1000 (
0#
#65000
b11011110101011011011111011101111 !
b11011110101011011011111011101111 +
1#
#66000
b10010001101000101011001111000 0
b10000 /
b110010001101101011001010110110101101000010110110011001001011101 -
b11011110101011011011111011101111 ,
0$
#70000
1'
b10010001101000101011001111000 &
b10010001101000101011001111000 )
b10000 "
b10000 (
0#
#75000
1#
#76000
b10000 .
0'
#80000
1$
b0 &
b0 )
0#
#85000
b10010001101000101011001111000 !
b10010001101000101011001111000 +
1#
#86000
b11001010111111101011101010111110 0
b111010001100101001011110111001001100101011000010110010000100000 -
b10010001101000101011001111000 ,
0$
#90000
1'
b11001010111111101011101010111110 &
b11001010111111101011101010111110 )
0#
#95000
1#
#96000
0'
#100000
1$
b0 &
b0 )
0#
#105000
b11001010111111101011101010111110 !
b11001010111111101011101010111110 +
1#
#106000
b10101010101010101010101010101010 0
b100000 /
b111001001110111011100100110100101110100011001010010000000100000 -
b11001010111111101011101010111110 ,
0$
#110000
1'
b10101010101010101010101010101010 &
b10101010101010101010101010101010 )
b100000 "
b100000 (
0#
#115000
1#
#116000
0'
#120000
1$
1'
b10111011101110111011101110111011 &
b10111011101110111011101110111011 )
0#
#125000
b10101010101010101010101010101010 !
b10101010101010101010101010101010 +
1#
#126000
b11011110101011010000000000000000 .
b10000001100100011000010111010001100001001000000010000000100000 -
b10101010101010101010101010101010 ,
0$
0'
#130000
1$
b0 &
b0 )
b11011110101011010000000000000000 "
b11011110101011010000000000000000 (
0#
#135000
b11011110101011011011111011101111 !
b11011110101011011011111011101111 +
1#
#136000
b110000101110000011100000110010101100100001000000010000000100000 -
b11011110101011011011111011101111 ,
0$
